{"default": {"Front Left Hip": "90", "Front Left Ankle": "90", "Front Right Hip": "90", "Front Right Ankle": "90", "Back Left Hip": "90", "Back Left Ankle": "90", "Back Right Hip": "90", "Back Right Ankle": "90"}, "90pos": {"Front Left Hip": "90", "Front Left Ankle": "90", "Front Right Hip": "90", "Front Right Ankle": "90", "Back Left Hip": "90", "Back Left Ankle": "90", "Back Right Hip": "90", "Back Right Ankle": "90"}, "stand": {"Front Left Ankle": "0", "Front Left Hip": "55", "Back Left Ankle": "0", "Back Left Hip": "139", "Front Right Ankle": "0", "Front Right Hip": "142", "Back Right Ankle": "0", "Back Right Hip": "55"}, "90": {"Front Left Ankle": "90", "Front Left Hip": "90", "Back Left Ankle": "90", "Back Left Hip": "90", "Front Right Ankle": "90", "Front Right Hip": "90", "Back Right Ankle": "90", "Back Right Hip": "90"}, "straightstand": {"Front Left Ankle": "0", "Front Left Hip": "90", "Back Left Ankle": "0", "Back Left Hip": "90", "Front Right Ankle": "0", "Front Right Hip": "90", "Back Right Ankle": "0", "Back Right Hip": "90"}}